listpy.py
listpy-0.0.1.dist-info/LICENSE
listpy-0.0.1.dist-info/METADATA
listpy-0.0.1.dist-info/WHEEL
listpy-0.0.1.dist-info/entry_points.txt
listpy-0.0.1.dist-info/top_level.txt
listpy-0.0.1.dist-info/RECORD
